{
    "sourceFile": "src/aida0710/pluginname/PluginName.php",
    "activeCommit": 0,
    "commits": [
        {
            "activePatchIndex": 2,
            "patches": [
                {
                    "date": 1724907961708,
                    "content": "Index: \n===================================================================\n--- \n+++ \n"
                },
                {
                    "date": 1724907979887,
                    "content": "Index: \n===================================================================\n--- \n+++ \n@@ -0,0 +1,24 @@\n+<?php\r\n+\r\n+declare(strict_types = 1);\r\n+\r\n+namespace aida0710\\plugin_name;\r\n+\r\n+use pocketmine\\plugin\\PluginBase;\r\n+\r\n+class PluginName extends PluginBase {\r\n+    /**\r\n+     * @return void\r\n+     */\r\n+    protected function onEnable(): void {\r\n+        $this->getLogger()->info('プラグインを読み込みました'); //PMMPの公式では非推奨の為、動作確認ができ次第削除してください。\r\n+    }\r\n+\r\n+    /**\r\n+     * @return void\r\n+     */\r\n+    protected function onDisable(): void {\r\n+        $this->getLogger()->info('LevelSystemを停止しました'); //PMMPの公式では非推奨の為、動作確認ができ次第削除してください。\r\n+    }\r\n+\r\n+}\r\n"
                },
                {
                    "date": 1724907987002,
                    "content": "Index: \n===================================================================\n--- \n+++ \n@@ -17,34 +17,8 @@\n     /**\r\n      * @return void\r\n      */\r\n     protected function onDisable(): void {\r\n-        $this->getLogger()->info('LevelSystemを停止しました'); //PMMPの公式では非推奨の為、動作確認ができ次第削除してください。\r\n+        $this->getLogger()->info('プラグインを停止しました'); //PMMPの公式では非推奨の為、動作確認ができ次第削除してください。\r\n     }\r\n \r\n }\r\n-<?php\r\n-\r\n-declare(strict_types = 1);\r\n-\r\n-namespace aida0710\\plugin_name;\r\n-\r\n-use pocketmine\\plugin\\PluginBase;\r\n-\r\n-class PluginName extends PluginBase {\r\n-    /**\r\n-     * @return void\r\n-     */\r\n-    protected function onEnable(): void {\r\n-        $this->getLogger()->info('LevelSystemを読み込みました'); //PMMPの公式では非推奨の為、動作確認ができ次第削除してください。\r\n-    }\r\n-\r\n-    /**\r\n-     * @return void\r\n-     */\r\n-    protected function onDisable(): void {\r\n-        $this->getLogger()->info('LevelSystemを停止しました'); //PMMPの公式では非推奨の為、動作確認ができ次第削除してください。\r\n-    }\r\n-}\r\n-\r\n-\r\n-}\r\n"
                }
            ],
            "date": 1724907961708,
            "name": "Commit-0",
            "content": "<?php\r\n\r\ndeclare(strict_types = 1);\r\n\r\nnamespace aida0710\\plugin_name;\r\n\r\nuse pocketmine\\plugin\\PluginBase;\r\n\r\nclass PluginName extends PluginBase {\r\n    /**\r\n     * @return void\r\n     */\r\n    protected function onEnable(): void {\r\n        $this->getLogger()->info('LevelSystemを読み込みました'); //PMMPの公式では非推奨の為、動作確認ができ次第削除してください。\r\n    }\r\n\r\n    /**\r\n     * @return void\r\n     */\r\n    protected function onDisable(): void {\r\n        $this->getLogger()->info('LevelSystemを停止しました'); //PMMPの公式では非推奨の為、動作確認ができ次第削除してください。\r\n    }\r\n}\r\n\r\n\r\n}\r\n"
        }
    ]
}